{
	"skill": [
		{
			"key": 1,
			"name": "스킬 1",
			"iconKey": "RedDragon",
			"skillType": 0,
			"cost": 0,
			"castType": 0,
			"enemyTargetType": 0,
			"enemyTargetCount": 0,
			"allyTargetType": 0,
			"allyTargetCount": 0,
			"attackRatio": 0,
			"healRatio": 0,
			"shield": 0,
			"shield_ValueType": 0,
			"draw": 1,
			"draw_DeckType": 0,
			"draw_TargetType": 0,
			"gainCost": 0,
			"excluded": 0,
			"disposable": 0,
			"addCard": "null",
			"shuffle_Deck": "null"
		},
		{
			"key": 2,
			"name": "스킬 2",
			"iconKey": "TheLich",
			"skillType": 0,
			"cost": 0,
			"castType": 0,
			"enemyTargetType": 0,
			"enemyTargetCount": 0,
			"allyTargetType": 0,
			"allyTargetCount": 0,
			"attackRatio": 0,
			"healRatio": 0,
			"shield": 0,
			"shield_ValueType": 0,
			"draw": 1,
			"draw_DeckType": 0,
			"draw_TargetType": 0,
			"gainCost": 0,
			"excluded": 0,
			"disposable": 0,
			"addCard": "null",
			"shuffle_Deck": "null"
		},
		{
			"key": 3,
			"name": "스킬 3",
			"iconKey": "Catssassin",
			"skillType": 0,
			"cost": 0,
			"castType": 0,
			"enemyTargetType": 0,
			"enemyTargetCount": 0,
			"allyTargetType": 0,
			"allyTargetCount": 0,
			"attackRatio": 0,
			"healRatio": 0,
			"shield": 0,
			"shield_ValueType": 0,
			"draw": 1,
			"draw_DeckType": 0,
			"draw_TargetType": 0,
			"gainCost": 0,
			"excluded": 0,
			"disposable": 0,
			"addCard": "null",
			"shuffle_Deck": "null"
		},
		{
			"key": 4,
			"name": "스킬 4",
			"iconKey": "FishKing",
			"skillType": 0,
			"cost": 0,
			"castType": 0,
			"enemyTargetType": 0,
			"enemyTargetCount": 0,
			"allyTargetType": 0,
			"allyTargetCount": 0,
			"attackRatio": 0,
			"healRatio": 0,
			"shield": 0,
			"shield_ValueType": 0,
			"draw": 1,
			"draw_DeckType": 0,
			"draw_TargetType": 0,
			"gainCost": 0,
			"excluded": 0,
			"disposable": 0,
			"addCard": "null",
			"shuffle_Deck": "null"
		},
		{
			"key": 5,
			"name": "스킬 5",
			"iconKey": "GoblinMage",
			"skillType": 0,
			"cost": 0,
			"castType": 0,
			"enemyTargetType": 0,
			"enemyTargetCount": 0,
			"allyTargetType": 0,
			"allyTargetCount": 0,
			"attackRatio": 0,
			"healRatio": 0,
			"shield": 0,
			"shield_ValueType": 0,
			"draw": 1,
			"draw_DeckType": 0,
			"draw_TargetType": 0,
			"gainCost": 0,
			"excluded": 0,
			"disposable": 0,
			"addCard": "null",
			"shuffle_Deck": "null"
		},
		{
			"key": 6,
			"name": "스킬 6",
			"iconKey": "HarpyStrike",
			"skillType": 0,
			"cost": 0,
			"castType": 0,
			"enemyTargetType": 0,
			"enemyTargetCount": 0,
			"allyTargetType": 0,
			"allyTargetCount": 0,
			"attackRatio": 0,
			"healRatio": 0,
			"shield": 0,
			"shield_ValueType": 0,
			"draw": 1,
			"draw_DeckType": 0,
			"draw_TargetType": 0,
			"gainCost": 0,
			"excluded": 0,
			"disposable": 0,
			"addCard": "null",
			"shuffle_Deck": "null"
		},
		{
			"key": 7,
			"name": "스킬 7",
			"iconKey": "NightClock",
			"skillType": 0,
			"cost": 0,
			"castType": 0,
			"enemyTargetType": 0,
			"enemyTargetCount": 0,
			"allyTargetType": 0,
			"allyTargetCount": 0,
			"attackRatio": 0,
			"healRatio": 0,
			"shield": 0,
			"shield_ValueType": 0,
			"draw": 1,
			"draw_DeckType": 0,
			"draw_TargetType": 0,
			"gainCost": 0,
			"excluded": 0,
			"disposable": 0,
			"addCard": "null",
			"shuffle_Deck": "null"
		},
		{
			"key": 8,
			"name": "스킬 8",
			"iconKey": "SlimeKnight",
			"skillType": 0,
			"cost": 0,
			"castType": 0,
			"enemyTargetType": 0,
			"enemyTargetCount": 0,
			"allyTargetType": 0,
			"allyTargetCount": 0,
			"attackRatio": 0,
			"healRatio": 0,
			"shield": 0,
			"shield_ValueType": 0,
			"draw": 1,
			"draw_DeckType": 0,
			"draw_TargetType": 0,
			"gainCost": 0,
			"excluded": 0,
			"disposable": 0,
			"addCard": "null",
			"shuffle_Deck": "null"
		},
		{
			"key": 9,
			"name": "스킬 9",
			"iconKey": "SlimeMage",
			"skillType": 0,
			"cost": 0,
			"castType": 0,
			"enemyTargetType": 0,
			"enemyTargetCount": 0,
			"allyTargetType": 0,
			"allyTargetCount": 0,
			"attackRatio": 0,
			"healRatio": 0,
			"shield": 0,
			"shield_ValueType": 0,
			"draw": 1,
			"draw_DeckType": 0,
			"draw_TargetType": 0,
			"gainCost": 0,
			"excluded": 0,
			"disposable": 0,
			"addCard": "null",
			"shuffle_Deck": "null"
		},
		{
			"key": 10,
			"name": "스킬 10",
			"iconKey": "SlimePrincess",
			"skillType": 0,
			"cost": 0,
			"castType": 0,
			"enemyTargetType": 0,
			"enemyTargetCount": 0,
			"allyTargetType": 0,
			"allyTargetCount": 0,
			"attackRatio": 0,
			"healRatio": 0,
			"shield": 0,
			"shield_ValueType": 0,
			"draw": 1,
			"draw_DeckType": 0,
			"draw_TargetType": 0,
			"gainCost": 0,
			"excluded": 0,
			"disposable": 0,
			"addCard": "null",
			"shuffle_Deck": "null"
		},
		{
			"key": 11,
			"name": "스킬 11",
			"iconKey": "TeaSpoonKnight",
			"skillType": 0,
			"cost": 0,
			"castType": 0,
			"enemyTargetType": 0,
			"enemyTargetCount": 0,
			"allyTargetType": 0,
			"allyTargetCount": 0,
			"attackRatio": 0,
			"healRatio": 0,
			"shield": 0,
			"shield_ValueType": 0,
			"draw": 1,
			"draw_DeckType": 0,
			"draw_TargetType": 0,
			"gainCost": 0,
			"excluded": 0,
			"disposable": 0,
			"addCard": "null",
			"shuffle_Deck": "null"
		},
		{
			"key": 12,
			"name": "스킬 12",
			"iconKey": "WanderingRabbit",
			"skillType": 0,
			"cost": 0,
			"castType": 0,
			"enemyTargetType": 0,
			"enemyTargetCount": 0,
			"allyTargetType": 0,
			"allyTargetCount": 0,
			"attackRatio": 0,
			"healRatio": 0,
			"shield": 0,
			"shield_ValueType": 0,
			"draw": 1,
			"draw_DeckType": 0,
			"draw_TargetType": 0,
			"gainCost": 0,
			"excluded": 0,
			"disposable": 0,
			"addCard": "null",
			"shuffle_Deck": "null"
		},
		{
			"key": 13,
			"name": "스킬 13",
			"iconKey": "SheepHug",
			"skillType": 0,
			"cost": 0,
			"castType": 0,
			"enemyTargetType": 0,
			"enemyTargetCount": 0,
			"allyTargetType": 0,
			"allyTargetCount": 0,
			"attackRatio": 0,
			"healRatio": 0,
			"shield": 0,
			"shield_ValueType": 0,
			"draw": 1,
			"draw_DeckType": 0,
			"draw_TargetType": 0,
			"gainCost": 0,
			"excluded": 0,
			"disposable": 0,
			"addCard": "null",
			"shuffle_Deck": "null"
		},
		{
			"key": 14,
			"name": "스킬 14",
			"iconKey": "SmokingWisp",
			"skillType": 0,
			"cost": 0,
			"castType": 0,
			"enemyTargetType": 0,
			"enemyTargetCount": 0,
			"allyTargetType": 0,
			"allyTargetCount": 0,
			"attackRatio": 0,
			"healRatio": 0,
			"shield": 0,
			"shield_ValueType": 0,
			"draw": 1,
			"draw_DeckType": 0,
			"draw_TargetType": 0,
			"gainCost": 0,
			"excluded": 0,
			"disposable": 0,
			"addCard": "null",
			"shuffle_Deck": "null"
		},
		{
			"key": 15,
			"name": "스킬 15",
			"iconKey": "SnowBeetle",
			"skillType": 0,
			"cost": 0,
			"castType": 0,
			"enemyTargetType": 0,
			"enemyTargetCount": 0,
			"allyTargetType": 0,
			"allyTargetCount": 0,
			"attackRatio": 0,
			"healRatio": 0,
			"shield": 0,
			"shield_ValueType": 0,
			"draw": 1,
			"draw_DeckType": 0,
			"draw_TargetType": 0,
			"gainCost": 0,
			"excluded": 0,
			"disposable": 0,
			"addCard": "null",
			"shuffle_Deck": "null"
		},
		{
			"key": 101,
			"name": "고블린 총격",
			"skillType": 0,
			"cost": 0,
			"castType": 0,
			"enemyTargetType": 0,
			"enemyTargetCount": 0,
			"allyTargetType": 0,
			"allyTargetCount": 0,
			"attackRatio": 0,
			"healRatio": 0,
			"shield": 0,
			"shield_ValueType": 0,
			"draw": 1,
			"draw_DeckType": 0,
			"draw_TargetType": 0,
			"gainCost": 0,
			"excluded": 0,
			"disposable": 0,
			"addCard": "null",
			"shuffle_Deck": "null"
		},
		{
			"key": 102,
			"name": "고블린 더블샷",
			"skillType": 0,
			"cost": 0,
			"castType": 0,
			"enemyTargetType": 0,
			"enemyTargetCount": 0,
			"allyTargetType": 0,
			"allyTargetCount": 0,
			"attackRatio": 0,
			"healRatio": 0,
			"shield": 0,
			"shield_ValueType": 0,
			"draw": 1,
			"draw_DeckType": 0,
			"draw_TargetType": 0,
			"gainCost": 0,
			"excluded": 0,
			"disposable": 0,
			"addCard": "null",
			"shuffle_Deck": "null"
		},
		{
			"key": 201,
			"name": "고블린 타격",
			"skillType": 0,
			"cost": 0,
			"castType": 0,
			"enemyTargetType": 0,
			"enemyTargetCount": 0,
			"allyTargetType": 0,
			"allyTargetCount": 0,
			"attackRatio": 0,
			"healRatio": 0,
			"shield": 0,
			"shield_ValueType": 0,
			"draw": 1,
			"draw_DeckType": 0,
			"draw_TargetType": 0,
			"gainCost": 0,
			"excluded": 0,
			"disposable": 0,
			"addCard": "null",
			"shuffle_Deck": "null"
		},
		{
			"key": 202,
			"name": "고블린 강타",
			"skillType": 0,
			"cost": 0,
			"castType": 0,
			"enemyTargetType": 0,
			"enemyTargetCount": 0,
			"allyTargetType": 0,
			"allyTargetCount": 0,
			"attackRatio": 0,
			"healRatio": 0,
			"shield": 0,
			"shield_ValueType": 0,
			"draw": 1,
			"draw_DeckType": 0,
			"draw_TargetType": 0,
			"gainCost": 0,
			"excluded": 0,
			"disposable": 0,
			"addCard": "null",
			"shuffle_Deck": "null"
		},
		{
			"key": 301,
			"name": "고블린 마법 공격",
			"skillType": 0,
			"cost": 0,
			"castType": 0,
			"enemyTargetType": 0,
			"enemyTargetCount": 0,
			"allyTargetType": 0,
			"allyTargetCount": 0,
			"attackRatio": 0,
			"healRatio": 0,
			"shield": 0,
			"shield_ValueType": 0,
			"draw": 1,
			"draw_DeckType": 0,
			"draw_TargetType": 0,
			"gainCost": 0,
			"excluded": 0,
			"disposable": 0,
			"addCard": "null",
			"shuffle_Deck": "null"
		},
		{
			"key": 302,
			"name": "고블린 광역 공격",
			"skillType": 0,
			"cost": 0,
			"castType": 0,
			"enemyTargetType": 0,
			"enemyTargetCount": 0,
			"allyTargetType": 0,
			"allyTargetCount": 0,
			"attackRatio": 0,
			"healRatio": 0,
			"shield": 0,
			"shield_ValueType": 0,
			"draw": 1,
			"draw_DeckType": 0,
			"draw_TargetType": 0,
			"gainCost": 0,
			"excluded": 0,
			"disposable": 0,
			"addCard": "null",
			"shuffle_Deck": "null"
		}
	]
}
